jinja_frontmatter.py
jinja_frontmatter-0.1.0.dist-info/LICENSE
jinja_frontmatter-0.1.0.dist-info/METADATA
jinja_frontmatter-0.1.0.dist-info/WHEEL
jinja_frontmatter-0.1.0.dist-info/RECORD
